alexapy/__init__.py
alexapy/alexaapi.py
alexapy/alexahttp2.py
alexapy/alexalogin.py
alexapy/alexaproxy.py
alexapy/alexawebsocket.py
alexapy/const.py
alexapy/errors.py
alexapy/helpers.py
alexapy-1.29.15.dist-info/METADATA
alexapy-1.29.15.dist-info/WHEEL
alexapy-1.29.15.dist-info/licenses/AUTHORS.md
alexapy-1.29.15.dist-info/licenses/LICENSE
alexapy-1.29.15.dist-info/RECORD
